clump/__init__.py
clump/model.py
clump-0.0.5.dist-info/LICENSE
clump-0.0.5.dist-info/METADATA
clump-0.0.5.dist-info/WHEEL
clump-0.0.5.dist-info/top_level.txt
clump-0.0.5.dist-info/RECORD
