Metadata-Version: 2.1
Name: clump
Version: 0.0.5
Summary: Easy-to-use package for grouping, tagging and finding similar documents, using advanced natural language processing techniques
Home-page: https://github.com/readikus/clump
Author: Ian Read
Author-email: ianharveyread@gmail.com
License: UNKNOWN
Platform: UNKNOWN
Classifier: Programming Language :: Python :: 3
Classifier: License :: OSI Approved :: MIT License
Classifier: Operating System :: OS Independent
Requires-Python: >=3.6
